bmcs_shell/__init__.py
bmcs_shell/api.py
bmcs_shell/version.py
bmcs_shell/folding/NOTES.md
bmcs_shell/folding/__init__.py
bmcs_shell/folding/class_diagram.puml
bmcs_shell/folding/wb_cell_lab_displ.ipynb
bmcs_shell/folding/analysis/__init__.py
bmcs_shell/folding/analysis/fets2d_mitc.py
bmcs_shell/folding/analysis/wb_fe_triangular_mesh.py
bmcs_shell/folding/analysis/wb_fe_triangular_mesh_switch_to_gmsh.py
bmcs_shell/folding/analysis/wb_fets2d3u1m_fe.py
bmcs_shell/folding/analysis/wb_shell_analysis.py
bmcs_shell/folding/analysis/abaqus/__init__.py
bmcs_shell/folding/analysis/abaqus/abaqus_link.py
bmcs_shell/folding/analysis/abaqus/abaqus_link_simple.py
bmcs_shell/folding/analysis/abaqus/abaqus_shell_manager.py
bmcs_shell/folding/analysis/atena/__init__.py
bmcs_shell/folding/analysis/atena/atena_exporter.py
bmcs_shell/folding/analysis/fem/__init__.py
bmcs_shell/folding/analysis/fem/bcs.py
bmcs_shell/folding/analysis/fem/fe_triangular_mesh.py
bmcs_shell/folding/analysis/fem/tri_xdomain_fe.py
bmcs_shell/folding/analysis/fem/tri_xdomain_fe_mitc.py
bmcs_shell/folding/analysis/fem/vmats2D_elastic.py
bmcs_shell/folding/analysis/fem/vmats_shell_elastic.py
bmcs_shell/folding/analysis/fem/xdomain_fe_grid.py
bmcs_shell/folding/analysis/fem/temp/__init__.py
bmcs_shell/folding/analysis/fem/temp/fets2d_mitc_1gp.py
bmcs_shell/folding/analysis/fem/temp/fets2d_mitc_2_gp_in_t_direction.py
bmcs_shell/folding/analysis/fem/temp/fets2d_mitc_7gp.py
bmcs_shell/folding/analysis/fem/temp/tri_xdomain_fe_mitc_with_global_trans.py
bmcs_shell/folding/analysis/fem/temp/tri_xdomain_fe_no_trans_to_compare_B_directly.py
bmcs_shell/folding/assembly/__init__.py
bmcs_shell/folding/assembly/wb_assembler.py
bmcs_shell/folding/assembly/wb_combinator.py
bmcs_shell/folding/assembly/wb_scanned_cell.py
bmcs_shell/folding/assembly/wb_scanned_cell_assembly.py
bmcs_shell/folding/geometry/__init__.py
bmcs_shell/folding/geometry/math_utils.py
bmcs_shell/folding/geometry/wb_geo_utils.py
bmcs_shell-0.0.8.dist-info/METADATA
bmcs_shell-0.0.8.dist-info/WHEEL
bmcs_shell-0.0.8.dist-info/top_level.txt
bmcs_shell-0.0.8.dist-info/RECORD
