Metadata-Version: 2.1
Name: bmcs-shell
Version: 0.0.8
Summary: Model components for analysis of BMCS shells.
Home-page: https://github.com/bmcs-group/bmcs_shell
Author: BMCS-Group
Author-email: rostislav.chudoba@rwt-aachen.de
License: MIT
Classifier: License :: OSI Approved :: MIT License
Classifier: Programming Language :: Python
Classifier: Programming Language :: Python :: 3
Classifier: Programming Language :: Python :: 3.6
Classifier: Programming Language :: Python :: Implementation :: CPython
Classifier: Programming Language :: Python :: Implementation :: PyPy
Requires-Python: >=3.6.0
